openfactcheck/__init__.py
openfactcheck/base.py
openfactcheck/cli.py
openfactcheck/errors.py
openfactcheck/solver.py
openfactcheck/state.py
openfactcheck/app/__init__.py
openfactcheck/app/app.py
openfactcheck/app/dialogs.py
openfactcheck/app/evaluate_factchecker.py
openfactcheck/app/evaluate_llm.py
openfactcheck/app/evaluate_response.py
openfactcheck/app/sidebar.py
openfactcheck/app/utils.py
openfactcheck/data/__init__.py
openfactcheck/data/factcheck-bench.jsonl
openfactcheck/data/factoolqa.jsonl
openfactcheck/data/factscore-bio.jsonl
openfactcheck/data/felm-wk.jsonl
openfactcheck/data/freshqa.jsonl
openfactcheck/data/selfaware.jsonl
openfactcheck/data/snowballing.jsonl
openfactcheck/evaluator/__init__.py
openfactcheck/evaluator/checker/__init__.py
openfactcheck/evaluator/checker/evaluate.py
openfactcheck/evaluator/llm/__init__.py
openfactcheck/evaluator/llm/evaluate.py
openfactcheck/evaluator/llm/evaluate_freetext.py
openfactcheck/evaluator/llm/evaluate_freshqa.py
openfactcheck/evaluator/llm/evaluate_selfaware.py
openfactcheck/evaluator/llm/evaluate_snowballing.py
openfactcheck/evaluator/llm/report.py
openfactcheck/evaluator/response/__init__.py
openfactcheck/evaluator/response/evaluate.py
openfactcheck/lib/__init__.py
openfactcheck/lib/config.py
openfactcheck/lib/utils.py
openfactcheck/services/__init__.py
openfactcheck/services/dynamodbinterface.py
openfactcheck/services/model.py
openfactcheck/solvers/__init__.py
openfactcheck/solvers/dummy/__init__.py
openfactcheck/solvers/dummy/confused_claim_examiner.py
openfactcheck/solvers/dummy/fake_claim_extractor.py
openfactcheck/solvers/dummy/ignorant_search_engine_retriever.py
openfactcheck/solvers/dummy/useless_response_regenerator.py
openfactcheck/solvers/factcheckgpt/factcheckgpt_cp.py
openfactcheck/solvers/factcheckgpt/factcheckgpt_rtv.py
openfactcheck/solvers/factcheckgpt/factcheckgpt_vfr.py
openfactcheck/solvers/factcheckgpt/factcheckgpt_utils/__init__.py
openfactcheck-0.3.15.dist-info/licenses/LICENSE
openfactcheck-0.3.15.dist-info/METADATA
openfactcheck-0.3.15.dist-info/WHEEL
openfactcheck-0.3.15.dist-info/top_level.txt
openfactcheck-0.3.15.dist-info/RECORD
