Metadata-Version: 2.4
Name: openfactcheck
Version: 0.3.15
Summary: An Open-source Factuality Evaluation Demo for LLMs
Author-email: Hasan Iqbal <hasan.iqbal@mbzuai.ac.ae>, Yuxia Wang <yuxia.wang@mbzuai.ac.ae>, Minghan Wang <minghan.wang@monash.edu>, Georgi Georgiev <geoergi@uni-sofia.bg>, Jiahui Geng <jiahui.geng@mbzuai.ac.ae>, Preslav Nakov <preslav.nakov@mbzuai.ac.ae>
Maintainer-email: Hasan Iqbal <hasan.iqbal@mbzuai.ac.ae>
License:                     GNU GENERAL PUBLIC LICENSE
Project-URL: Bug Tracker, https://github.com/hasaniqbal777/openfactcheck/issues
Project-URL: Documentation, https://openfactcheck.readthedocs.io
Project-URL: Homepage, https://github.com/hasaniqbal777/openfactcheck
Project-URL: Repository, https://github.com/hasaniqbal777/openfactcheck
Keywords: NLP,deep learning,transformer,pytorch,factuality evaluation
Classifier: Development Status :: 3 - Alpha
Classifier: Intended Audience :: Developers
Classifier: Intended Audience :: Education
Classifier: Intended Audience :: Science/Research
Classifier: License :: OSI Approved :: GNU General Public License v3 (GPLv3)
Classifier: Operating System :: OS Independent
Classifier: Programming Language :: Python :: 3
Classifier: Programming Language :: Python :: 3.10
Classifier: Programming Language :: Python :: 3.11
Classifier: Topic :: Scientific/Engineering :: Artificial Intelligence
Requires-Python: >=3.10
License-File: LICENSE
Provides-Extra: docs
Requires-Dist: sphinx; extra == "docs"
Requires-Dist: sphinx-design; extra == "docs"
Requires-Dist: sphinx-favicon; extra == "docs"
Requires-Dist: sphinx-autobuild; extra == "docs"
Requires-Dist: sphinx-copybutton; extra == "docs"
Requires-Dist: sphinxext-rediraffe; extra == "docs"
Requires-Dist: sphinx-togglebutton; extra == "docs"
Requires-Dist: pydata-sphinx-theme; extra == "docs"
Requires-Dist: myst-parser; extra == "docs"
Dynamic: license-file
